{
  "timestamp": 1712841747,
  "ensemble_score": 0.51,
  "confidence": 0.67,
  "severity": "medium",
  "anomaly_type": "point",
  "affected_sensors": [
    "sensor_1",
    "sensor_2",
    "sensor_21",
    "sensor_22"
  ],
  "detection_driver": "iforest",
  "model_outputs": {
    "zscore": {
      "score": 10.279429296739442,
      "is_anomaly": 1,
      "score_norm": 0.049264057418698944
    },
    "iforest": {
      "score": 0.052309938619765406,
      "is_anomaly": 1,
      "score_norm": 0.9320295719623027
    },
    "lstm": {
      "score": 0.25365749419142436,
      "is_anomaly": 0,
      "score_norm": 0.5501600087139907
    }
  },
  "consensus": {
    "votes": 2,
    "agreement": {
      "zscore_lstm": 100,
      "lstm_iforest": 2,
      "zscore_iforest": 102
    }
  }
}